{
	"name": "SnowflakeTable_DimCategory",
	"properties": {
		"linkedServiceName": {
			"referenceName": "Snowflake_IMDB",
			"type": "LinkedServiceReference"
		},
		"annotations": [],
		"type": "SnowflakeV2Table",
		"schema": [
			{
				"name": "CATEGORY_ID_SK",
				"type": "NUMBER",
				"precision": 38,
				"scale": 0
			},
			{
				"name": "CATEGORY_NAME",
				"type": "VARCHAR"
			},
			{
				"name": "JOB_ID",
				"type": "VARCHAR"
			},
			{
				"name": "LOAD_DT",
				"type": "DATE"
			}
		],
		"typeProperties": {
			"schema": "IMDB_SCHEMA",
			"table": "DIM_CATEGORY"
		}
	}
}